{"@context": ["https://geojson.org/geojson-ld/geojson-context.jsonld", {"@version": "1.1", "wx": "https://api.weather.gov/ontology#", "geo": "http://www.opengis.net/ont/geosparql#", "unit": "http://codes.wmo.int/common/unit/", "@vocab": "https://api.weather.gov/ontology#"}], "type": "Feature", "geometry": {"type": "Polygon", "coordinates": [[[-89.2471, 37.6668], [-89.2459, 37.689], [-89.274, 37.69], [-89.2752, 37.6677], [-89.2471, 37.6668]]]}, "properties": {"units": "us", "forecastGenerator": "BaselineForecastGenerator", "generatedAt": "2026-02-27T13:36:03+00:00", "updateTime": "2026-02-27T12:57:08+00:00", "validTimes": "2026-02-27T06:00:00+00:00/P7DT19H", "elevation": {"unitCode": "wmoUnit:m", "value": 152.0952}, "periods": [{"number": 1, "name": "Today", "startTime": "2026-02-27T07:00:00-06:00", "endTime": "2026-02-27T18:00:00-06:00", "isDaytime": true, "temperature": 70, "temperatureUnit": "F", "temperatureTrend": null, "probabilityOfPrecipitation": {"unitCode": "wmoUnit:percent", "value": 0}, "windSpeed": "2 to 12 mph", "windDirection": "SW", "icon": "https://api.weather.gov/icons/land/day/skc?size=medium", "shortForecast": "Sunny", "detailedForecast": "Sunny. High near 70, with temperatures falling to around 68 in the afternoon. Southwest wind 2 to 12 mph."}, {"number": 2, "name": "Tonight", "startTime": "2026-02-27T18:00:00-06:00", "endTime": "2026-02-28T06:00:00-06:00", "isDaytime": false, "temperature": 44, "temperatureUnit": "F", "temperatureTrend": null, "probabilityOfPrecipitation": {"unitCode": "wmoUnit:percent", "value": 1}, "windSpeed": "5 to 9 mph", "windDirection": "SW", "icon": "https://api.weather.gov/icons/land/night/skc?size=medium", "shortForecast": "Clear", "detailedForecast": "Clear. Low around 44, with temperatures rising to around 46 overnight. Southwest wind 5 to 9 mph."}, {"number": 3, "name": "Saturday", "startTime": "2026-02-28T06:00:00-06:00", "endTime": "2026-02-28T18:00:00-06:00", "isDaytime": true, "temperature": 68, "temperatureUnit": "F", "temperatureTrend": null, "probabilityOfPrecipitation": {"unitCode": "wmoUnit:percent", "value": 5}, "windSpeed": "7 mph", "windDirection": "SSE", "icon": "https://api.weather.gov/icons/land/day/few?size=medium", "shortForecast": "Sunny", "detailedForecast": "Sunny. High near 68, with temperatures falling to around 66 in the afternoon. South southeast wind around 7 mph."}, {"number": 4, "name": "Saturday Night", "startTime": "2026-02-28T18:00:00-06:00", "endTime": "2026-03-01T06:00:00-06:00", "isDaytime": false, "temperature": 35, "temperatureUnit": "F", "temperatureTrend": null, "probabilityOfPrecipitation": {"unitCode": "wmoUnit:percent", "value": 14}, "windSpeed": "7 to 12 mph", "windDirection": "WNW", "icon": "https://api.weather.gov/icons/land/night/sct?size=medium", "shortForecast": "Partly Cloudy", "detailedForecast": "Partly cloudy, with a low around 35. West northwest wind 7 to 12 mph, with gusts as high as 20 mph."}, {"number": 5, "name": "Sunday", "startTime": "2026-03-01T06:00:00-06:00", "endTime": "2026-03-01T18:00:00-06:00", "isDaytime": true, "temperature": 50, "temperatureUnit": "F", "temperatureTrend": null, "probabilityOfPrecipitation": {"unitCode": "wmoUnit:percent", "value": 9}, "windSpeed": "12 mph", "windDirection": "NE", "icon": "https://api.weather.gov/icons/land/day/bkn?size=medium", "shortForecast": "Mostly Cloudy", "detailedForecast": "Mostly cloudy, with a high near 50. Northeast wind around 12 mph, with gusts as high as 18 mph."}, {"number": 6, "name": "Sunday Night", "startTime": "2026-03-01T18:00:00-06:00", "endTime": "2026-03-02T06:00:00-06:00", "isDaytime": false, "temperature": 36, "temperatureUnit": "F", "temperatureTrend": null, "probabilityOfPrecipitation": {"unitCode": "wmoUnit:percent", "value": 69}, "windSpeed": "10 mph", "windDirection": "ENE", "icon": "https://api.weather.gov/icons/land/night/rain_showers,50/rain_showers,70?size=medium", "shortForecast": "Rain Showers Likely", "detailedForecast": "Rain showers likely. Cloudy, with a low around 36. East northeast wind around 10 mph. Chance of precipitation is 70%."}, {"number": 7, "name": "Monday", "startTime": "2026-03-02T06:00:00-06:00", "endTime": "2026-03-02T18:00:00-06:00", "isDaytime": true, "temperature": 46, "temperatureUnit": "F", "temperatureTrend": null, "probabilityOfPrecipitation": {"unitCode": "wmoUnit:percent", "value": 43}, "windSpeed": "9 mph", "windDirection": "ENE", "icon": "https://api.weather.gov/icons/land/day/rain_showers,40/rain_showers,20?size=medium", "shortForecast": "Chance Rain Showers", "detailedForecast": "A chance of rain showers. Mostly cloudy, with a high near 46. East northeast wind around 9 mph."}, {"number": 8, "name": "Monday Night", "startTime": "2026-03-02T18:00:00-06:00", "endTime": "2026-03-03T06:00:00-06:00", "isDaytime": false, "temperature": 39, "temperatureUnit": "F", "temperatureTrend": null, "probabilityOfPrecipitation": {"unitCode": "wmoUnit:percent", "value": 43}, "windSpeed": "7 mph", "windDirection": "ESE", "icon": "https://api.weather.gov/icons/land/night/rain_showers,30/rain_showers,40?size=medium", "shortForecast": "Chance Rain Showers", "detailedForecast": "A chance of rain showers. Mostly cloudy, with a low around 39. East southeast wind around 7 mph."}, {"number": 9, "name": "Tuesday", "startTime": "2026-03-03T06:00:00-06:00", "endTime": "2026-03-03T18:00:00-06:00", "isDaytime": true, "temperature": 57, "temperatureUnit": "F", "temperatureTrend": null, "probabilityOfPrecipitation": {"unitCode": "wmoUnit:percent", "value": 61}, "windSpeed": "9 mph", "windDirection": "SSW", "icon": "https://api.weather.gov/icons/land/day/rain_showers,60/tsra,60?size=medium", "shortForecast": "Rain Showers Likely", "detailedForecast": "Rain showers likely before noon, then showers and thunderstorms likely. Cloudy, with a high near 57. South southwest wind around 9 mph."}, {"number": 10, "name": "Tuesday Night", "startTime": "2026-03-03T18:00:00-06:00", "endTime": "2026-03-04T06:00:00-06:00", "isDaytime": false, "temperature": 48, "temperatureUnit": "F", "temperatureTrend": null, "probabilityOfPrecipitation": {"unitCode": "wmoUnit:percent", "value": 62}, "windSpeed": "7 mph", "windDirection": "SSE", "icon": "https://api.weather.gov/icons/land/night/tsra,60?size=medium", "shortForecast": "Showers And Thunderstorms Likely", "detailedForecast": "Showers and thunderstorms likely. Mostly cloudy, with a low around 48. South southeast wind around 7 mph."}, {"number": 11, "name": "Wednesday", "startTime": "2026-03-04T06:00:00-06:00", "endTime": "2026-03-04T18:00:00-06:00", "isDaytime": true, "temperature": 66, "temperatureUnit": "F", "temperatureTrend": null, "probabilityOfPrecipitation": {"unitCode": "wmoUnit:percent", "value": 54}, "windSpeed": "9 mph", "windDirection": "SSE", "icon": "https://api.weather.gov/icons/land/day/tsra,50?size=medium", "shortForecast": "Chance Showers And Thunderstorms", "detailedForecast": "A chance of showers and thunderstorms. Cloudy, with a high near 66. South southeast wind around 9 mph."}, {"number": 12, "name": "Wednesday Night", "startTime": "2026-03-04T18:00:00-06:00", "endTime": "2026-03-05T06:00:00-06:00", "isDaytime": false, "temperature": 56, "temperatureUnit": "F", "temperatureTrend": null, "probabilityOfPrecipitation": {"unitCode": "wmoUnit:percent", "value": 55}, "windSpeed": "8 to 12 mph", "windDirection": "S", "icon": "https://api.weather.gov/icons/land/night/tsra,40/tsra,60?size=medium", "shortForecast": "Showers And Thunderstorms Likely", "detailedForecast": "Showers and thunderstorms likely. Mostly cloudy, with a low around 56. South wind 8 to 12 mph, with gusts as high as 21 mph."}, {"number": 13, "name": "Thursday", "startTime": "2026-03-05T06:00:00-06:00", "endTime": "2026-03-05T18:00:00-06:00", "isDaytime": true, "temperature": 69, "temperatureUnit": "F", "temperatureTrend": null, "probabilityOfPrecipitation": {"unitCode": "wmoUnit:percent", "value": 59}, "windSpeed": "10 to 14 mph", "windDirection": "SSW", "icon": "https://api.weather.gov/icons/land/day/rain_showers,60/rain_showers,50?size=medium", "shortForecast": "Rain Showers Likely", "detailedForecast": "Rain showers likely. Mostly cloudy, with a high near 69. South southwest wind 10 to 14 mph, with gusts as high as 22 mph."}, {"number": 14, "name": "Thursday Night", "startTime": "2026-03-05T18:00:00-06:00", "endTime": "2026-03-06T06:00:00-06:00", "isDaytime": false, "temperature": 56, "temperatureUnit": "F", "temperatureTrend": null, "probabilityOfPrecipitation": {"unitCode": "wmoUnit:percent", "value": 51}, "windSpeed": "10 mph", "windDirection": "S", "icon": "https://api.weather.gov/icons/land/night/rain_showers,40/rain_showers,50?size=medium", "shortForecast": "Chance Rain Showers", "detailedForecast": "A chance of rain showers. Mostly cloudy, with a low around 56. South wind around 10 mph."}]}}