{"@context": ["https://geojson.org/geojson-ld/geojson-context.jsonld", {"@version": "1.1", "wx": "https://api.weather.gov/ontology#", "geo": "http://www.opengis.net/ont/geosparql#", "unit": "http://codes.wmo.int/common/unit/", "@vocab": "https://api.weather.gov/ontology#"}], "type": "Feature", "geometry": {"type": "Polygon", "coordinates": [[[-89.2740424, 37.6899564], [-89.2752298, 37.6677151], [-89.24712690000001, 37.666772900000005], [-89.24593360000001, 37.68901410000001], [-89.2740424, 37.6899564]]]}, "properties": {"units": "us", "forecastGenerator": "BaselineForecastGenerator", "generatedAt": "2024-08-15T17:36:02+00:00", "updateTime": "2024-08-15T17:23:39+00:00", "validTimes": "2024-08-15T11:00:00+00:00/P7DT14H", "elevation": {"unitCode": "wmoUnit:m", "value": 152.0952}, "periods": [{"number": 1, "name": "This Afternoon", "startTime": "2024-08-15T12:00:00-05:00", "endTime": "2024-08-15T18:00:00-05:00", "isDaytime": true, "temperature": 89, "temperatureUnit": "F", "temperatureTrend": "", "probabilityOfPrecipitation": {"unitCode": "wmoUnit:percent", "value": 40}, "windSpeed": "9 mph", "windDirection": "S", "icon": "https://api.weather.gov/icons/land/day/tsra_hi,40?size=medium", "shortForecast": "Chance Showers And Thunderstorms", "detailedForecast": "A chance of showers and thunderstorms. Some of the storms could produce heavy rain. Mostly sunny, with a high near 89. South wind around 9 mph. Chance of precipitation is 40%."}, {"number": 2, "name": "Tonight", "startTime": "2024-08-15T18:00:00-05:00", "endTime": "2024-08-16T06:00:00-05:00", "isDaytime": false, "temperature": 72, "temperatureUnit": "F", "temperatureTrend": "", "probabilityOfPrecipitation": {"unitCode": "wmoUnit:percent", "value": 60}, "windSpeed": "8 mph", "windDirection": "SSW", "icon": "https://api.weather.gov/icons/land/night/tsra,60?size=medium", "shortForecast": "Showers And Thunderstorms Likely", "detailedForecast": "Showers and thunderstorms likely. Some of the storms could produce heavy rain. Mostly cloudy. Low around 72, with temperatures rising to around 74 overnight. South southwest wind around 8 mph. Chance of precipitation is 60%."}, {"number": 3, "name": "Friday", "startTime": "2024-08-16T06:00:00-05:00", "endTime": "2024-08-16T18:00:00-05:00", "isDaytime": true, "temperature": 90, "temperatureUnit": "F", "temperatureTrend": "", "probabilityOfPrecipitation": {"unitCode": "wmoUnit:percent", "value": 40}, "windSpeed": "8 mph", "windDirection": "WSW", "icon": "https://api.weather.gov/icons/land/day/tsra_hi,40?size=medium", "shortForecast": "Chance Showers And Thunderstorms", "detailedForecast": "A chance of showers and thunderstorms. Mostly sunny, with a high near 90. West southwest wind around 8 mph. Chance of precipitation is 40%."}, {"number": 4, "name": "Friday Night", "startTime": "2024-08-16T18:00:00-05:00", "endTime": "2024-08-17T06:00:00-05:00", "isDaytime": false, "temperature": 71, "temperatureUnit": "F", "temperatureTrend": "", "probabilityOfPrecipitation": {"unitCode": "wmoUnit:percent", "value": 30}, "windSpeed": "2 to 6 mph", "windDirection": "SW", "icon": "https://api.weather.gov/icons/land/night/tsra_hi,30?size=medium", "shortForecast": "Chance Showers And Thunderstorms", "detailedForecast": "A chance of showers and thunderstorms before 1am, then a chance of showers and thunderstorms between 1am and 4am, then a chance of showers and thunderstorms. Partly cloudy, with a low around 71. Southwest wind 2 to 6 mph. Chance of precipitation is 30%."}, {"number": 5, "name": "Saturday", "startTime": "2024-08-17T06:00:00-05:00", "endTime": "2024-08-17T18:00:00-05:00", "isDaytime": true, "temperature": 88, "temperatureUnit": "F", "temperatureTrend": "", "probabilityOfPrecipitation": {"unitCode": "wmoUnit:percent", "value": 30}, "windSpeed": "3 to 8 mph", "windDirection": "WNW", "icon": "https://api.weather.gov/icons/land/day/tsra_hi,30/tsra_hi,20?size=medium", "shortForecast": "Chance Showers And Thunderstorms", "detailedForecast": "A chance of showers and thunderstorms. Sunny, with a high near 88. West northwest wind 3 to 8 mph. Chance of precipitation is 30%."}, {"number": 6, "name": "Saturday Night", "startTime": "2024-08-17T18:00:00-05:00", "endTime": "2024-08-18T06:00:00-05:00", "isDaytime": false, "temperature": 65, "temperatureUnit": "F", "temperatureTrend": "", "probabilityOfPrecipitation": {"unitCode": "wmoUnit:percent", "value": 20}, "windSpeed": "2 to 7 mph", "windDirection": "NNW", "icon": "https://api.weather.gov/icons/land/night/tsra_hi,20/few?size=medium", "shortForecast": "Slight Chance Showers And Thunderstorms then Mostly Clear", "detailedForecast": "A slight chance of showers and thunderstorms before 7pm. Mostly clear, with a low around 65. North northwest wind 2 to 7 mph. Chance of precipitation is 20%."}, {"number": 7, "name": "Sunday", "startTime": "2024-08-18T06:00:00-05:00", "endTime": "2024-08-18T18:00:00-05:00", "isDaytime": true, "temperature": 84, "temperatureUnit": "F", "temperatureTrend": "", "probabilityOfPrecipitation": {"unitCode": "wmoUnit:percent", "value": null}, "windSpeed": "3 to 9 mph", "windDirection": "NNW", "icon": "https://api.weather.gov/icons/land/day/few?size=medium", "shortForecast": "Sunny", "detailedForecast": "Sunny, with a high near 84. North northwest wind 3 to 9 mph."}, {"number": 8, "name": "Sunday Night", "startTime": "2024-08-18T18:00:00-05:00", "endTime": "2024-08-19T06:00:00-05:00", "isDaytime": false, "temperature": 64, "temperatureUnit": "F", "temperatureTrend": "", "probabilityOfPrecipitation": {"unitCode": "wmoUnit:percent", "value": null}, "windSpeed": "2 to 7 mph", "windDirection": "N", "icon": "https://api.weather.gov/icons/land/night/few?size=medium", "shortForecast": "Mostly Clear", "detailedForecast": "Mostly clear, with a low around 64. North wind 2 to 7 mph."}, {"number": 9, "name": "Monday", "startTime": "2024-08-19T06:00:00-05:00", "endTime": "2024-08-19T18:00:00-05:00", "isDaytime": true, "temperature": 84, "temperatureUnit": "F", "temperatureTrend": "", "probabilityOfPrecipitation": {"unitCode": "wmoUnit:percent", "value": null}, "windSpeed": "3 to 8 mph", "windDirection": "N", "icon": "https://api.weather.gov/icons/land/day/few?size=medium", "shortForecast": "Sunny", "detailedForecast": "Sunny, with a high near 84. North wind 3 to 8 mph."}, {"number": 10, "name": "Monday Night", "startTime": "2024-08-19T18:00:00-05:00", "endTime": "2024-08-20T06:00:00-05:00", "isDaytime": false, "temperature": 61, "temperatureUnit": "F", "temperatureTrend": "", "probabilityOfPrecipitation": {"unitCode": "wmoUnit:percent", "value": null}, "windSpeed": "2 to 7 mph", "windDirection": "NNE", "icon": "https://api.weather.gov/icons/land/night/few?size=medium", "shortForecast": "Mostly Clear", "detailedForecast": "Mostly clear, with a low around 61. North northeast wind 2 to 7 mph."}, {"number": 11, "name": "Tuesday", "startTime": "2024-08-20T06:00:00-05:00", "endTime": "2024-08-20T18:00:00-05:00", "isDaytime": true, "temperature": 84, "temperatureUnit": "F", "temperatureTrend": "", "probabilityOfPrecipitation": {"unitCode": "wmoUnit:percent", "value": null}, "windSpeed": "3 to 7 mph", "windDirection": "NNE", "icon": "https://api.weather.gov/icons/land/day/few?size=medium", "shortForecast": "Sunny", "detailedForecast": "Sunny, with a high near 84. North northeast wind 3 to 7 mph."}, {"number": 12, "name": "Tuesday Night", "startTime": "2024-08-20T18:00:00-05:00", "endTime": "2024-08-21T06:00:00-05:00", "isDaytime": false, "temperature": 61, "temperatureUnit": "F", "temperatureTrend": "", "probabilityOfPrecipitation": {"unitCode": "wmoUnit:percent", "value": null}, "windSpeed": "2 to 6 mph", "windDirection": "NE", "icon": "https://api.weather.gov/icons/land/night/few?size=medium", "shortForecast": "Mostly Clear", "detailedForecast": "Mostly clear, with a low around 61. Northeast wind 2 to 6 mph."}, {"number": 13, "name": "Wednesday", "startTime": "2024-08-21T06:00:00-05:00", "endTime": "2024-08-21T18:00:00-05:00", "isDaytime": true, "temperature": 83, "temperatureUnit": "F", "temperatureTrend": "", "probabilityOfPrecipitation": {"unitCode": "wmoUnit:percent", "value": null}, "windSpeed": "6 mph", "windDirection": "ENE", "icon": "https://api.weather.gov/icons/land/day/few?size=medium", "shortForecast": "Sunny", "detailedForecast": "Sunny, with a high near 83. East northeast wind around 6 mph."}, {"number": 14, "name": "Wednesday Night", "startTime": "2024-08-21T18:00:00-05:00", "endTime": "2024-08-22T06:00:00-05:00", "isDaytime": false, "temperature": 61, "temperatureUnit": "F", "temperatureTrend": "", "probabilityOfPrecipitation": {"unitCode": "wmoUnit:percent", "value": null}, "windSpeed": "5 mph", "windDirection": "ENE", "icon": "https://api.weather.gov/icons/land/night/few?size=medium", "shortForecast": "Mostly Clear", "detailedForecast": "Mostly clear, with a low around 61. East northeast wind around 5 mph."}]}}