{"@context": ["https://geojson.org/geojson-ld/geojson-context.jsonld", {"@version": "1.1", "wx": "https://api.weather.gov/ontology#", "geo": "http://www.opengis.net/ont/geosparql#", "unit": "http://codes.wmo.int/common/unit/", "@vocab": "https://api.weather.gov/ontology#"}], "type": "Feature", "geometry": {"type": "Polygon", "coordinates": [[[-89.2740424, 37.6899564], [-89.2752298, 37.6677151], [-89.24712690000001, 37.666772900000005], [-89.24593360000001, 37.68901410000001], [-89.2740424, 37.6899564]]]}, "properties": {"units": "us", "forecastGenerator": "BaselineForecastGenerator", "generatedAt": "2024-10-27T22:36:03+00:00", "updateTime": "2024-10-27T19:26:00+00:00", "validTimes": "2024-10-27T13:00:00+00:00/P7DT12H", "elevation": {"unitCode": "wmoUnit:m", "value": 152.0952}, "periods": [{"number": 1, "name": "This Afternoon", "startTime": "2024-10-27T17:00:00-05:00", "endTime": "2024-10-27T18:00:00-05:00", "isDaytime": true, "temperature": 69, "temperatureUnit": "F", "temperatureTrend": "", "probabilityOfPrecipitation": {"unitCode": "wmoUnit:percent", "value": null}, "windSpeed": "5 mph", "windDirection": "E", "icon": "https://api.weather.gov/icons/land/day/skc?size=medium", "shortForecast": "Sunny", "detailedForecast": "Sunny. High near 69, with temperatures falling to around 67 in the afternoon. East wind around 5 mph."}, {"number": 2, "name": "Tonight", "startTime": "2024-10-27T18:00:00-05:00", "endTime": "2024-10-28T06:00:00-05:00", "isDaytime": false, "temperature": 44, "temperatureUnit": "F", "temperatureTrend": "", "probabilityOfPrecipitation": {"unitCode": "wmoUnit:percent", "value": null}, "windSpeed": "3 mph", "windDirection": "SE", "icon": "https://api.weather.gov/icons/land/night/skc?size=medium", "shortForecast": "Clear", "detailedForecast": "Clear, with a low around 44. Southeast wind around 3 mph."}, {"number": 3, "name": "Monday", "startTime": "2024-10-28T06:00:00-05:00", "endTime": "2024-10-28T18:00:00-05:00", "isDaytime": true, "temperature": 78, "temperatureUnit": "F", "temperatureTrend": "", "probabilityOfPrecipitation": {"unitCode": "wmoUnit:percent", "value": null}, "windSpeed": "3 to 12 mph", "windDirection": "SSE", "icon": "https://api.weather.gov/icons/land/day/sct?size=medium", "shortForecast": "Mostly Sunny", "detailedForecast": "Mostly sunny. High near 78, with temperatures falling to around 76 in the afternoon. South southeast wind 3 to 12 mph, with gusts as high as 20 mph."}, {"number": 4, "name": "Monday Night", "startTime": "2024-10-28T18:00:00-05:00", "endTime": "2024-10-29T06:00:00-05:00", "isDaytime": false, "temperature": 64, "temperatureUnit": "F", "temperatureTrend": "", "probabilityOfPrecipitation": {"unitCode": "wmoUnit:percent", "value": null}, "windSpeed": "8 to 13 mph", "windDirection": "S", "icon": "https://api.weather.gov/icons/land/night/bkn?size=medium", "shortForecast": "Mostly Cloudy", "detailedForecast": "Mostly cloudy, with a low around 64. South wind 8 to 13 mph, with gusts as high as 23 mph."}, {"number": 5, "name": "Tuesday", "startTime": "2024-10-29T06:00:00-05:00", "endTime": "2024-10-29T18:00:00-05:00", "isDaytime": true, "temperature": 82, "temperatureUnit": "F", "temperatureTrend": "", "probabilityOfPrecipitation": {"unitCode": "wmoUnit:percent", "value": null}, "windSpeed": "13 to 17 mph", "windDirection": "SSW", "icon": "https://api.weather.gov/icons/land/day/few?size=medium", "shortForecast": "Sunny", "detailedForecast": "Sunny, with a high near 82. South southwest wind 13 to 17 mph, with gusts as high as 29 mph."}, {"number": 6, "name": "Tuesday Night", "startTime": "2024-10-29T18:00:00-05:00", "endTime": "2024-10-30T06:00:00-05:00", "isDaytime": false, "temperature": 65, "temperatureUnit": "F", "temperatureTrend": "", "probabilityOfPrecipitation": {"unitCode": "wmoUnit:percent", "value": null}, "windSpeed": "15 mph", "windDirection": "S", "icon": "https://api.weather.gov/icons/land/night/sct?size=medium", "shortForecast": "Partly Cloudy", "detailedForecast": "Partly cloudy, with a low around 65. South wind around 15 mph, with gusts as high as 25 mph."}, {"number": 7, "name": "Wednesday", "startTime": "2024-10-30T06:00:00-05:00", "endTime": "2024-10-30T18:00:00-05:00", "isDaytime": true, "temperature": 82, "temperatureUnit": "F", "temperatureTrend": "", "probabilityOfPrecipitation": {"unitCode": "wmoUnit:percent", "value": null}, "windSpeed": "14 to 18 mph", "windDirection": "S", "icon": "https://api.weather.gov/icons/land/day/few?size=medium", "shortForecast": "Sunny", "detailedForecast": "Sunny, with a high near 82. South wind 14 to 18 mph, with gusts as high as 30 mph."}, {"number": 8, "name": "Wednesday Night", "startTime": "2024-10-30T18:00:00-05:00", "endTime": "2024-10-31T06:00:00-05:00", "isDaytime": false, "temperature": 60, "temperatureUnit": "F", "temperatureTrend": "", "probabilityOfPrecipitation": {"unitCode": "wmoUnit:percent", "value": null}, "windSpeed": "16 mph", "windDirection": "S", "icon": "https://api.weather.gov/icons/land/night/bkn/tsra_hi?size=medium", "shortForecast": "Mostly Cloudy then Showers And Thunderstorms Likely", "detailedForecast": "Showers and thunderstorms likely after 1am. Mostly cloudy, with a low around 60. South wind around 16 mph, with gusts as high as 26 mph."}, {"number": 9, "name": "Thursday", "startTime": "2024-10-31T06:00:00-05:00", "endTime": "2024-10-31T18:00:00-05:00", "isDaytime": true, "temperature": 69, "temperatureUnit": "F", "temperatureTrend": "", "probabilityOfPrecipitation": {"unitCode": "wmoUnit:percent", "value": null}, "windSpeed": "8 to 15 mph", "windDirection": "W", "icon": "https://api.weather.gov/icons/land/day/tsra?size=medium", "shortForecast": "Showers And Thunderstorms", "detailedForecast": "Showers and thunderstorms. Mostly cloudy, with a high near 69. West wind 8 to 15 mph, with gusts as high as 23 mph."}, {"number": 10, "name": "Thursday Night", "startTime": "2024-10-31T18:00:00-05:00", "endTime": "2024-11-01T06:00:00-05:00", "isDaytime": false, "temperature": 43, "temperatureUnit": "F", "temperatureTrend": "", "probabilityOfPrecipitation": {"unitCode": "wmoUnit:percent", "value": null}, "windSpeed": "3 to 7 mph", "windDirection": "N", "icon": "https://api.weather.gov/icons/land/night/tsra_hi?size=medium", "shortForecast": "Chance Showers And Thunderstorms", "detailedForecast": "A chance of showers and thunderstorms before 1am. Partly cloudy, with a low around 43. North wind 3 to 7 mph."}, {"number": 11, "name": "Friday", "startTime": "2024-11-01T06:00:00-05:00", "endTime": "2024-11-01T18:00:00-05:00", "isDaytime": true, "temperature": 64, "temperatureUnit": "F", "temperatureTrend": "", "probabilityOfPrecipitation": {"unitCode": "wmoUnit:percent", "value": null}, "windSpeed": "6 mph", "windDirection": "NE", "icon": "https://api.weather.gov/icons/land/day/few?size=medium", "shortForecast": "Sunny", "detailedForecast": "Sunny, with a high near 64. Northeast wind around 6 mph."}, {"number": 12, "name": "Friday Night", "startTime": "2024-11-01T18:00:00-05:00", "endTime": "2024-11-02T06:00:00-05:00", "isDaytime": false, "temperature": 47, "temperatureUnit": "F", "temperatureTrend": "", "probabilityOfPrecipitation": {"unitCode": "wmoUnit:percent", "value": null}, "windSpeed": "6 mph", "windDirection": "E", "icon": "https://api.weather.gov/icons/land/night/rain_showers?size=medium", "shortForecast": "Chance Rain Showers", "detailedForecast": "A chance of rain showers after 7pm. Partly cloudy, with a low around 47. East wind around 6 mph."}, {"number": 13, "name": "Saturday", "startTime": "2024-11-02T06:00:00-05:00", "endTime": "2024-11-02T18:00:00-05:00", "isDaytime": true, "temperature": 72, "temperatureUnit": "F", "temperatureTrend": "", "probabilityOfPrecipitation": {"unitCode": "wmoUnit:percent", "value": null}, "windSpeed": "8 mph", "windDirection": "SE", "icon": "https://api.weather.gov/icons/land/day/rain_showers?size=medium", "shortForecast": "Chance Rain Showers", "detailedForecast": "A chance of rain showers. Partly sunny, with a high near 72. Southeast wind around 8 mph."}, {"number": 14, "name": "Saturday Night", "startTime": "2024-11-02T18:00:00-05:00", "endTime": "2024-11-03T06:00:00-06:00", "isDaytime": false, "temperature": 57, "temperatureUnit": "F", "temperatureTrend": "", "probabilityOfPrecipitation": {"unitCode": "wmoUnit:percent", "value": null}, "windSpeed": "7 mph", "windDirection": "SSE", "icon": "https://api.weather.gov/icons/land/night/rain_showers?size=medium", "shortForecast": "Chance Rain Showers", "detailedForecast": "A chance of rain showers. Mostly cloudy, with a low around 57. South southeast wind around 7 mph."}]}}